.gitignore
LICENSE.txt
MANIFEST.in
README.md
requirements.txt
setup.cfg
setup.py
priest/__init__.py
priest.egg-info/PKG-INFO
priest.egg-info/SOURCES.txt
priest.egg-info/dependency_links.txt
priest.egg-info/requires.txt
priest.egg-info/top_level.txt
priest/data/afternoon.data
priest/data/evening.data
priest/data/morning.data
priest/data/night.data
priest/data/fonts/clearsans.ttf
priest/data/images/afternoon/afternoon1.jpg
priest/data/images/afternoon/afternoon2.jpg
priest/data/images/afternoon/afternoon3.jpg
priest/data/images/afternoon/afternoon4.jpg
priest/data/images/evening/evening1.jpg
priest/data/images/evening/evening2.jpg
priest/data/images/evening/evening3.jpg
priest/data/images/evening/evening4.jpg
priest/data/images/evening/evening5.jpg
priest/data/images/morning/morning1.jpg
priest/data/images/morning/morning2.jpg
priest/data/images/morning/morning3.jpg
priest/data/images/morning/morning4.jpg
priest/data/images/morning/morning5.jpg
priest/data/images/night/night1.jpg
priest/data/images/night/night2.jpg
priest/data/images/night/night3.jpg
priest/data/images/night/night4.jpg
priest/data/images/night/night5.jpg
priest/data/images/night/night6.jpg
priest/lib/__init__.py
priest/lib/core.py
priest/lib/msg_generator.py
priest/lib/utilities.py