Metadata-Version: 1.1
Name: priest
Version: 0.5
Summary: Generate wishes from your command line with full customization.
Home-page: https://github.com/black-perl/priest
Author: Ankush Sharma
Author-email: ankprahsar@gmail.com
License: MIT
Download-URL: https://github.com/black-perl/priest/tarball/0.5
Keywords: priest,automated-wishes
Platform: UNKNOWN
